containerdispatch/__init__.py
containerdispatch/find_impl.py
containerdispatch/main.py
containerdispatch/mro.py
containerdispatch/utils.py
containerdispatch-0.1.2.dist-info/licenses/LICENSE
containerdispatch-0.1.2.dist-info/METADATA
containerdispatch-0.1.2.dist-info/WHEEL
containerdispatch-0.1.2.dist-info/top_level.txt
containerdispatch-0.1.2.dist-info/RECORD
