Metadata-Version: 2.4
Name: containerdispatch
Version: 0.1.2
Summary: a singledispatch alternative for PEP-585 type hinted functions
Requires-Python: >=3.12
License-File: LICENSE
Dynamic: license-file
